fancy_gym/__init__.py
fancy_gym/black_box/__init__.py
fancy_gym/black_box/black_box_wrapper.py
fancy_gym/black_box/raw_interface_wrapper.py
fancy_gym/black_box/controller/__init__.py
fancy_gym/black_box/controller/base_controller.py
fancy_gym/black_box/controller/meta_world_controller.py
fancy_gym/black_box/controller/pd_controller.py
fancy_gym/black_box/controller/pos_controller.py
fancy_gym/black_box/controller/vel_controller.py
fancy_gym/black_box/factory/__init__.py
fancy_gym/black_box/factory/basis_generator_factory.py
fancy_gym/black_box/factory/controller_factory.py
fancy_gym/black_box/factory/phase_generator_factory.py
fancy_gym/black_box/factory/trajectory_generator_factory.py
fancy_gym/dmc/__init__.py
fancy_gym/dmc/manipulation/__init__.py
fancy_gym/dmc/manipulation/reach_site/__init__.py
fancy_gym/dmc/manipulation/reach_site/mp_wrapper.py
fancy_gym/dmc/suite/__init__.py
fancy_gym/dmc/suite/ball_in_cup/__init__.py
fancy_gym/dmc/suite/ball_in_cup/mp_wrapper.py
fancy_gym/dmc/suite/cartpole/__init__.py
fancy_gym/dmc/suite/cartpole/mp_wrapper.py
fancy_gym/dmc/suite/reacher/__init__.py
fancy_gym/dmc/suite/reacher/mp_wrapper.py
fancy_gym/envs/__init__.py
fancy_gym/envs/registry.py
fancy_gym/envs/classic_control/__init__.py
fancy_gym/envs/classic_control/utils.py
fancy_gym/envs/classic_control/base_reacher/__init__.py
fancy_gym/envs/classic_control/base_reacher/base_reacher.py
fancy_gym/envs/classic_control/base_reacher/base_reacher_direct.py
fancy_gym/envs/classic_control/base_reacher/base_reacher_torque.py
fancy_gym/envs/classic_control/hole_reacher/__init__.py
fancy_gym/envs/classic_control/hole_reacher/hole_reacher.py
fancy_gym/envs/classic_control/hole_reacher/hr_dist_vel_acc_reward.py
fancy_gym/envs/classic_control/hole_reacher/hr_simple_reward.py
fancy_gym/envs/classic_control/hole_reacher/hr_unbounded_reward.py
fancy_gym/envs/classic_control/hole_reacher/mp_wrapper.py
fancy_gym/envs/classic_control/simple_reacher/__init__.py
fancy_gym-0.3.0.dist-info/LICENSE
fancy_gym-0.3.0.dist-info/METADATA
fancy_gym-0.3.0.dist-info/WHEEL
fancy_gym-0.3.0.dist-info/top_level.txt
fancy_gym-0.3.0.dist-info/RECORD
