Metadata-Version: 2.1
Name: fancy-gym
Version: 0.3.0
Summary: Fancy Gym: Unifying interface for various RL benchmarks with support for Black Box approaches.
Author-email: Fabian Otto <fabian.otto@uni-tuebingen.de>, Onur Celik <celik@kit.edu>, Dominik Roth <fancy_gym@dominik-roth.eu>, Hongyi Zhou <hongyi.zhou@kit.edu>
License: MIT License
Project-URL: Homepage, https://github.com/ALRhub/fancy_gym/
Project-URL: Bug Tracker, https://github.com/ALRhub/fancy_gym/issues
Classifier: Development Status :: 4 - Beta
Classifier: Intended Audience :: Science/Research
Classifier: License :: OSI Approved :: MIT License
Classifier: Natural Language :: English
Classifier: Operating System :: OS Independent
Classifier: Topic :: Scientific/Engineering :: Artificial Intelligence
Classifier: Programming Language :: Python :: 3
Classifier: Programming Language :: Python :: 3.7
Classifier: Programming Language :: Python :: 3.8
Classifier: Programming Language :: Python :: 3.9
Classifier: Programming Language :: Python :: 3.10
Classifier: Programming Language :: Python :: 3.11
Requires-Python: >=3.7
License-File: LICENSE
Requires-Dist: gymnasium[mujoco] (>=0.26.0)
Requires-Dist: mp-pytorch (<=0.1.3)
Requires-Dist: mujoco (==2.3.3)
Requires-Dist: toml
Provides-Extra: all
Requires-Dist: Shimmy (==1.0.0) ; extra == 'all'
Requires-Dist: cython (<3) ; extra == 'all'
Requires-Dist: gymnasium[box2d,mujoco] (>=0.26.0) ; extra == 'all'
Requires-Dist: jax (>=0.4.0) ; extra == 'all'
Requires-Dist: jaxlib (>=0.4.0) ; extra == 'all'
Requires-Dist: mujoco-py (<2.2,>=2.1) ; extra == 'all'
Requires-Dist: mujoco (==2.3.3) ; extra == 'all'
Requires-Dist: mushroom-rl ; extra == 'all'
Requires-Dist: shimmy[dm-control] ; extra == 'all'
Provides-Extra: box2d
Requires-Dist: gymnasium[box2d] (>=0.26.0) ; extra == 'box2d'
Provides-Extra: dmc
Requires-Dist: Shimmy (==1.0.0) ; extra == 'dmc'
Requires-Dist: shimmy[dm-control] ; extra == 'dmc'
Provides-Extra: jax
Requires-Dist: jax (>=0.4.0) ; extra == 'jax'
Requires-Dist: jaxlib (>=0.4.0) ; extra == 'jax'
Provides-Extra: mujoco-legacy
Requires-Dist: cython (<3) ; extra == 'mujoco-legacy'
Requires-Dist: mujoco-py (<2.2,>=2.1) ; extra == 'mujoco-legacy'
Provides-Extra: mushroom-rl
Requires-Dist: mushroom-rl ; extra == 'mushroom-rl'
Provides-Extra: testing
Requires-Dist: Shimmy (==1.0.0) ; extra == 'testing'
Requires-Dist: cython (<3) ; extra == 'testing'
Requires-Dist: gymnasium[box2d,mujoco] (>=0.26.0) ; extra == 'testing'
Requires-Dist: jax (>=0.4.0) ; extra == 'testing'
Requires-Dist: jaxlib (>=0.4.0) ; extra == 'testing'
Requires-Dist: mujoco-py (<2.2,>=2.1) ; extra == 'testing'
Requires-Dist: mujoco (==2.3.3) ; extra == 'testing'
Requires-Dist: mushroom-rl ; extra == 'testing'
Requires-Dist: pytest ; extra == 'testing'
Requires-Dist: shimmy[dm-control] ; extra == 'testing'
